cogconverter/VERSION
cogconverter/__init__.py
cogconverter/converter.py
cogconverter/validator.py
cogconverter/config/__init__.py
cogconverter/config/default_config.py
cogconverter/config/logging_config.py
cogconverter/src/__init__.py
cogconverter/src/create_alpha.py
cogconverter/src/metadata.py
cogconverter/src/pyramid.py
cogconverter-0.2.2.dist-info/LICENSE
cogconverter-0.2.2.dist-info/METADATA
cogconverter-0.2.2.dist-info/WHEEL
cogconverter-0.2.2.dist-info/top_level.txt
cogconverter-0.2.2.dist-info/RECORD
