Metadata-Version: 2.1
Name: cogconverter
Version: 0.2.2
Summary: Utility to convert raster dataset to Cloud Optimized GeoTIFFs
Home-page: https://github.com/ManishSahu53/cogconverter.git
Author: Manish Sahu
Author-email: manish.sahu.civ13@iitbhu.ac.in
License: GPLv3+
Keywords: GIS,Cloud,GDAL
Platform: UNKNOWN
Classifier: License :: OSI Approved :: GNU General Public License v3 or later (GPLv3+)
Classifier: Programming Language :: Python :: 3.6
Classifier: Programming Language :: Python :: 3.7
Classifier: Topic :: Scientific/Engineering :: GIS
Classifier: Topic :: Utilities
Requires-Dist: numpy
Requires-Dist: tqdm
Provides-Extra: dev
Requires-Dist: numpy ; extra == 'dev'
Requires-Dist: argparse ; extra == 'dev'
Requires-Dist: tqdm ; extra == 'dev'
